CHANGELOG.txt
ISSUES.txt
MANIFEST.in
README.txt
ciss.py
conftest.py
distribute_setup.py
setup.py
test_ciss.py
ciss.egg-info/PKG-INFO
ciss.egg-info/SOURCES.txt
ciss.egg-info/dependency_links.txt
ciss.egg-info/entry_points.txt
ciss.egg-info/not-zip-safe
ciss.egg-info/requires.txt
ciss.egg-info/top_level.txt
doc/.rel-0.1.0.txt.swp
doc/Makefile
doc/changelog.txt
doc/conf.py
doc/docindex.txt
doc/index.txt
doc/rel-0.1.0.txt
doc/tutorial.txt
doc/_templates/indexsidebar.html
doc/_templates/layout.html