Metadata-Version: 1.0
Name: ciss
Version: 0.2
Summary: ciss: code-centered single "ISSUES.txt" issue tracking
Home-page: http://codespeak.net/ciss
Author: holger krekel
Author-email: holger at merlinux.eu
License: MIT license
Platform: unix
Platform: linux
Platform: osx
Platform: cygwin
Platform: win32
Classifier: Development Status :: 3 - Alpha
Classifier: Intended Audience :: Developers
Classifier: License :: OSI Approved :: MIT License
Classifier: Operating System :: POSIX
Classifier: Operating System :: Microsoft :: Windows
Classifier: Operating System :: MacOS :: MacOS X
Classifier: Topic :: Utilities
Classifier: Intended Audience :: Developers
Classifier: Programming Language :: Python
